cli/__init__.py
cli/auth.py
cli/config.py
cli/main.py
cli/commands/__init__.py
cli/commands/generate.py
cli/commands/offline.py
cli/commands/online.py
cli/commands/useless.py
cli/commands/utils.py
cli/local_model/__init__.py
cli/local_model/cli_integration.py
cli/local_model/code_formatter.py
cli/local_model/generate_tests.py
cli/local_model/generate_tests_optimized.py
cli/local_model/main_orchestrator.py
cli/local_model/model_downloader.py
cli/local_model/offline_test_generator.py
cli/local_model/optimized_orchestrator.py
cli/local_model/prompt_handler.py
cli/local_model/resource_manager.py
cli/local_model/run_example.py
cli/local_model/runtime_installer.py
cli/local_model/server_manager.py
cli/local_model/testgenie_offline_cli.py
test_genie_test-1.0.5.dist-info/METADATA
test_genie_test-1.0.5.dist-info/WHEEL
test_genie_test-1.0.5.dist-info/entry_points.txt
test_genie_test-1.0.5.dist-info/top_level.txt
test_genie_test-1.0.5.dist-info/RECORD
