Metadata-Version: 2.4
Name: test_genie_test
Version: 1.0.5
Summary: AI-powered CLI tool to auto-generate test cases for Python, C++, and Java code with both online and offline modes
Author-email: Kushagra Wadhwa <testgenieofficial@gmail.com>
License-Expression: MIT
Project-URL: Homepage, https://thetestgenie.com
Project-URL: Documentation, https://thetestgenie.com/docs
Project-URL: Repository, https://github.com/testgenie/cli
Project-URL: Issues, https://github.com/testgenie/cli/issues
Project-URL: Pricing, https://thetestgenie.com/pricing
Keywords: testing,test-generation,ai,cli,python,cpp,java,pytest,unittest,gtest,junit
Classifier: Development Status :: 5 - Production/Stable
Classifier: Intended Audience :: Developers
Classifier: Programming Language :: Python :: 3
Classifier: Programming Language :: Python :: 3.8
Classifier: Programming Language :: Python :: 3.9
Classifier: Programming Language :: Python :: 3.10
Classifier: Programming Language :: Python :: 3.11
Classifier: Programming Language :: Python :: 3.12
Classifier: Topic :: Software Development :: Testing
Classifier: Topic :: Software Development :: Quality Assurance
Requires-Python: >=3.8
Requires-Dist: click>=8.1.7
Requires-Dist: requests>=2.31.0
Requires-Dist: pathlib2>=2.3.7
Requires-Dist: llama-cpp-python>=0.2.0
Requires-Dist: fastapi>=0.100.0
Requires-Dist: uvicorn>=0.23.0
Requires-Dist: psutil>=5.9.0
Provides-Extra: dev
Requires-Dist: pytest>=7.0.0; extra == "dev"
Requires-Dist: black>=23.0.0; extra == "dev"
Requires-Dist: flake8>=6.0.0; extra == "dev"
Requires-Dist: mypy>=1.0.0; extra == "dev"
Provides-Extra: offline
Requires-Dist: llama-cpp-python>=0.2.0; extra == "offline"
Requires-Dist: fastapi>=0.100.0; extra == "offline"
Requires-Dist: uvicorn>=0.23.0; extra == "offline"
Requires-Dist: psutil>=5.9.0; extra == "offline"
